setup.py
the_metrix/__init__.py
the_metrix.egg-info/PKG-INFO
the_metrix.egg-info/SOURCES.txt
the_metrix.egg-info/dependency_links.txt
the_metrix.egg-info/top_level.txt